MANIFEST.in
README.md
VERSION
setup.py
hitch/code_that_does_things.py
hitch/key.py
hitchbuild/__init__.py
hitchbuild/build.py
hitchbuild/utils.py
hitchbuild.egg-info/PKG-INFO
hitchbuild.egg-info/SOURCES.txt
hitchbuild.egg-info/dependency_links.txt
hitchbuild.egg-info/not-zip-safe
hitchbuild.egg-info/requires.txt
hitchbuild.egg-info/top_level.txt