Metadata-Version: 2.1
Name: hitchbuild
Version: 0.6.0
Summary: Building blocks for a build system.
Home-page: https://hitchbuild.readthedocs.org/
Author: Colm O'Connor
Author-email: colm.oconnor.github@gmail.com
License: AGPL
Keywords: hitchdev framework build
Platform: UNKNOWN
Classifier: Development Status :: 3 - Alpha
Classifier: Intended Audience :: Developers
Classifier: License :: OSI Approved :: GNU Affero General Public License v3 or later (AGPLv3+)
Classifier: Topic :: Software Development :: Quality Assurance
Classifier: Topic :: Software Development :: Testing
Classifier: Topic :: Software Development :: Libraries
Classifier: Operating System :: Unix
Classifier: Environment :: Console
Classifier: Programming Language :: Python :: 3
Classifier: Programming Language :: Python :: 3.3
Classifier: Programming Language :: Python :: 3.4
Classifier: Programming Language :: Python :: 3.5
